amazon_wishlist_exporter/__init__.py
amazon_wishlist_exporter/__main__.py
amazon_wishlist_exporter/cli.py
amazon_wishlist_exporter/exporter.py
amazon_wishlist_exporter/utils/__init__.py
amazon_wishlist_exporter/utils/locale_.py
amazon_wishlist_exporter/utils/locale_collator.py
amazon_wishlist_exporter/utils/logger_config.py
amazon_wishlist_exporter/utils/scraper.py
amazon_wishlist_exporter-2024.12.7.dist-info/METADATA
amazon_wishlist_exporter-2024.12.7.dist-info/WHEEL
amazon_wishlist_exporter-2024.12.7.dist-info/entry_points.txt
amazon_wishlist_exporter-2024.12.7.dist-info/licenses/LICENSE
amazon_wishlist_exporter-2024.12.7.dist-info/RECORD
