Metadata-Version: 2.3
Name: amazon-wishlist-exporter
Version: 2024.12.7
Summary: Export Amazon wishlist metadata to JSON
Project-URL: Homepage, https://github.com/nateify/amazon-wishlist-exporter
Project-URL: Documentation, https://github.com/nateify/amazon-wishlist-exporter#readme
Author-email: nateify <nateify@users.noreply.github.com>
License: MIT License
Keywords: amazon,amazon-wishlist,scraper,wishlist
Classifier: Environment :: Console
Classifier: License :: OSI Approved :: MIT License
Classifier: Operating System :: OS Independent
Classifier: Programming Language :: Python
Classifier: Programming Language :: Python :: 3
Classifier: Programming Language :: Python :: 3.9
Classifier: Programming Language :: Python :: 3.10
Classifier: Programming Language :: Python :: 3.11
Classifier: Programming Language :: Python :: 3.12
Classifier: Programming Language :: Python :: 3.13
Classifier: Topic :: Utilities
Requires-Python: >=3.9
Requires-Dist: amazoncaptcha>=0.5.11
Requires-Dist: babel~=2.16
Requires-Dist: curl-cffi~=0.7.3
Requires-Dist: dateparser~=1.2.0
Requires-Dist: price-parser~=0.3.4
Requires-Dist: selectolax~=0.3.26
Requires-Dist: tenacity~=9.0.0
Provides-Extra: icu
Requires-Dist: pyicu>=2.12; extra == 'icu'
